recordio-0.1.7.data/purelib/recordio/__init__.py
recordio-0.1.7.data/purelib/recordio/librecordio.so
recordio-0.1.7.data/purelib/recordio/recordio.py
recordio-0.1.7.data/purelib/recordio/recordio_test.py
recordio-0.1.7.dist-info/METADATA
recordio-0.1.7.dist-info/RECORD
recordio-0.1.7.dist-info/WHEEL
recordio-0.1.7.dist-info/top_level.txt
